.travis.yml
CHANGES.rst
MANIFEST.in
README.rst
setup.py
tox.ini
docs/Makefile
docs/source/api.rst
docs/source/changelog.rst
docs/source/conf.py
docs/source/index.rst
docs/source/api/modules.rst
docs/source/api/thriftpool.app.rst
docs/source/api/thriftpool.bin.rst
docs/source/api/thriftpool.components.rst
docs/source/api/thriftpool.controllers.rst
docs/source/api/thriftpool.remote.rst
docs/source/api/thriftpool.request.rst
docs/source/api/thriftpool.rpc.rst
docs/source/api/thriftpool.rst
docs/source/api/thriftpool.utils.dispatch.rst
docs/source/api/thriftpool.utils.rst
docs/source/getting-started/first_steps.rst
docs/source/getting-started/index.rst
docs/source/getting-started/installation.rst
thriftpool/__init__.py
thriftpool/base.py
thriftpool/exceptions.py
thriftpool/signals.py
thriftpool.egg-info/PKG-INFO
thriftpool.egg-info/SOURCES.txt
thriftpool.egg-info/dependency_links.txt
thriftpool.egg-info/entry_points.txt
thriftpool.egg-info/not-zip-safe
thriftpool.egg-info/requires.txt
thriftpool.egg-info/top_level.txt
thriftpool/app/__init__.py
thriftpool/app/_state.py
thriftpool/app/base.py
thriftpool/app/config.py
thriftpool/app/daemon.py
thriftpool/app/loader.py
thriftpool/app/log.py
thriftpool/app/slots.py
thriftpool/bin/__init__.py
thriftpool/bin/base.py
thriftpool/bin/thriftpoolctl.py
thriftpool/bin/thriftpoold.py
thriftpool/bin/thriftworker.py
thriftpool/components/__init__.py
thriftpool/components/base.py
thriftpool/components/loop.py
thriftpool/components/utils.py
thriftpool/components/manager/__init__.py
thriftpool/components/manager/acceptors.py
thriftpool/components/manager/gaffer.py
thriftpool/components/manager/listeners.py
thriftpool/components/manager/loop.py
thriftpool/components/manager/processes.py
thriftpool/components/manager/reaper.py
thriftpool/components/manager/tornado.py
thriftpool/components/worker/__init__.py
thriftpool/components/worker/acceptors.py
thriftpool/components/worker/loop.py
thriftpool/components/worker/pb_broker.py
thriftpool/components/worker/services.py
thriftpool/components/worker/watchdog.py
thriftpool/components/worker/worker.py
thriftpool/controllers/__init__.py
thriftpool/controllers/base.py
thriftpool/controllers/manager.py
